<?xml version="1.0" encoding="UTF-8"?>
<metadata xml:lang="en"><Esri><CreaDate>20211215</CreaDate><CreaTime>16350400</CreaTime><ArcGISFormat>1.0</ArcGISFormat><SyncOnce>TRUE</SyncOnce><DataProperties><lineage><Process ToolSource="c:\program files (x86)\arcgis\desktop10.7\ArcToolbox\Toolboxes\Data Management Tools.tbx\CalculateField" Date="20210422" Time="142707">CalculateField Population_WardOrCommuneLevel District_Name "District "&amp;mid( [District_Name],6,12) VB #</Process><Process ToolSource="c:\program files (x86)\arcgis\desktop10.7\ArcToolbox\Toolboxes\Data Management Tools.tbx\CalculateField" Date="20210422" Time="142730">CalculateField Population_WardOrCommuneLevel District_Name "Binh Tan District" VB #</Process><Process ToolSource="c:\program files (x86)\arcgis\desktop10.7\ArcToolbox\Toolboxes\Data Management Tools.tbx\CalculateField" Date="20210422" Time="142755">CalculateField Population_WardOrCommuneLevel District_Name "Binh Tan" VB #</Process><Process ToolSource="c:\program files (x86)\arcgis\desktop10.7\ArcToolbox\Toolboxes\Data Management Tools.tbx\CalculateField" Date="20210422" Time="142807">CalculateField Population_WardOrCommuneLevel District_Name "Binh Thanh" VB #</Process><Process ToolSource="c:\program files (x86)\arcgis\desktop10.7\ArcToolbox\Toolboxes\Data Management Tools.tbx\CalculateField" Date="20210422" Time="142816">CalculateField Population_WardOrCommuneLevel District_Name "Go Vap" VB #</Process><Process ToolSource="c:\program files (x86)\arcgis\desktop10.7\ArcToolbox\Toolboxes\Data Management Tools.tbx\CalculateField" Date="20210422" Time="142829">CalculateField Population_WardOrCommuneLevel District_Name "Phu Nhuan" VB #</Process><Process ToolSource="c:\program files (x86)\arcgis\desktop10.7\ArcToolbox\Toolboxes\Data Management Tools.tbx\CalculateField" Date="20210422" Time="142839">CalculateField Population_WardOrCommuneLevel District_Name "Tan Binh" VB #</Process><Process ToolSource="c:\program files (x86)\arcgis\desktop10.7\ArcToolbox\Toolboxes\Data Management Tools.tbx\CalculateField" Date="20210422" Time="143519">CalculateField Population_WardOrCommuneLevel District_Name "Tan Phu" VB #</Process><Process ToolSource="c:\program files (x86)\arcgis\desktop10.7\ArcToolbox\Toolboxes\Data Management Tools.tbx\CalculateField" Date="20210422" Time="143529">CalculateField Population_WardOrCommuneLevel District_Name "Thu Duc" VB #</Process><Process ToolSource="c:\program files (x86)\arcgis\desktop10.7\ArcToolbox\Toolboxes\Data Management Tools.tbx\CalculateField" Date="20210422" Time="143601">CalculateField Population_WardOrCommuneLevel District_Name "Hoc Mon" VB #</Process><Process ToolSource="c:\program files (x86)\arcgis\desktop10.7\ArcToolbox\Toolboxes\Data Management Tools.tbx\CalculateField" Date="20210422" Time="143611">CalculateField Population_WardOrCommuneLevel District_Name "Nha Be" VB #</Process><Process ToolSource="c:\program files (x86)\arcgis\desktop10.7\ArcToolbox\Toolboxes\Data Management Tools.tbx\CalculateField" Date="20210422" Time="143621">CalculateField Population_WardOrCommuneLevel District_Name "Cu Chi" VB #</Process><Process ToolSource="c:\program files (x86)\arcgis\desktop10.7\ArcToolbox\Toolboxes\Data Management Tools.tbx\CalculateField" Date="20210422" Time="143630">CalculateField Population_WardOrCommuneLevel District_Name "Can Gio" VB #</Process><Process ToolSource="c:\program files (x86)\arcgis\desktop10.7\ArcToolbox\Toolboxes\Data Management Tools.tbx\CalculateField" Date="20210422" Time="143639">CalculateField Population_WardOrCommuneLevel District_Name "Binh Chanh" VB #</Process><Process ToolSource="c:\program files (x86)\arcgis\desktop10.7\ArcToolbox\Toolboxes\Data Management Tools.tbx\CalculateField" Date="20210422" Time="143713">CalculateField Population_WardOrCommuneLevel Commune_Name "Ward "&amp;mid( [Commune_Name],8,10) VB #</Process><Process ToolSource="c:\program files (x86)\arcgis\desktop10.7\ArcToolbox\Toolboxes\Data Management Tools.tbx\CalculateField" Date="20210422" Time="143727">CalculateField Population_WardOrCommuneLevel Commune_Name "Ward "&amp;mid( [Commune_Name],8,10) VB #</Process><Process ToolSource="c:\program files (x86)\arcgis\desktop10.7\ArcToolbox\Toolboxes\Data Management Tools.tbx\CalculateField" Date="20210527" Time="151434">CalculateField Adminitration_WardAndCommuneLevel QHPX "[District_Name]&amp;"_"&amp; [Commune_Name]" VB #</Process><Process ToolSource="c:\program files (x86)\arcgis\desktop10.7\ArcToolbox\Toolboxes\Data Management Tools.tbx\CalculateField" Date="20210527" Time="151859">CalculateField Adminitration_WardAndCommuneLevel QHPX "[Commune_Name]&amp;"_"&amp;[District_Name] " VB #</Process><Process ToolSource="c:\program files (x86)\arcgis\desktop10.7\ArcToolbox\Toolboxes\Data Management Tools.tbx\CalculateField" Date="20210527" Time="151919">CalculateField Adminitration_WardAndCommuneLevel QHPX "[Commune_Name]&amp;"_"&amp;[District_Name] &amp;" District"" VB #</Process><Process ToolSource="c:\program files (x86)\arcgis\desktop10.7\ArcToolbox\Toolboxes\Data Management Tools.tbx\CalculateField" Date="20210527" Time="151935">CalculateField Adminitration_WardAndCommuneLevel QHPX "[Commune_Name]&amp;"_"&amp;[District_Name] &amp;" District"" VB #</Process><Process ToolSource="c:\program files (x86)\arcgis\desktop10.7\ArcToolbox\Toolboxes\Data Management Tools.tbx\CalculateField" Date="20210527" Time="155042">CalculateField Adminitration_WardAndCommuneLevel QHPX "[Commune_Name]&amp;" "&amp; [Level] &amp;"_"&amp;[District_Name] " VB #</Process><Process ToolSource="c:\program files (x86)\arcgis\desktop10.7\ArcToolbox\Toolboxes\Data Management Tools.tbx\CalculateField" Date="20210527" Time="155050">CalculateField Adminitration_WardAndCommuneLevel QHPX "[Commune_Name]&amp;" "&amp; [Level] &amp;"_"&amp;[District_Name] &amp;" District"" VB #</Process><Process ToolSource="c:\program files (x86)\arcgis\desktop10.7\ArcToolbox\Toolboxes\Data Management Tools.tbx\CalculateField" Date="20210527" Time="155248">CalculateField Adminitration_WardAndCommuneLevel QHPX "[Commune_Name]&amp;"_"&amp;[District_Name] &amp;" District"" VB #</Process></lineage><itemProps><itemLocation><linkage Sync="TRUE">file://\\DESKTOP-D79EU4H\G$\!!!!!!MyTask\005. SaiGon Penisula\1. Ranh\RanhGuiLenServer\Boundary.gdb</linkage><protocol Sync="TRUE">Local Area Network</protocol></itemLocation></itemProps></DataProperties></Esri></metadata>
